typyn/__init__.py
typyn/main.py
typyn/data/quotes/english.json
typyn/data/quotes/español.json
typyn/data/words/en-1000.txt
typyn/data/words/es-1000.txt
typyn/resources/intro_animation.py
typyn/user_data/player_data.json
typyn-1.0.17.dist-info/LICENSE
typyn-1.0.17.dist-info/METADATA
typyn-1.0.17.dist-info/WHEEL
typyn-1.0.17.dist-info/entry_points.txt
typyn-1.0.17.dist-info/top_level.txt
typyn-1.0.17.dist-info/RECORD
