Metadata-Version: 2.1
Name: typyn
Version: 1.0.17
Summary: A terminal-based typing game built in Python
Home-page: https://github.com/san-fernandez/typyn
Author: Santiago Fernández
Author-email: santifernandezok1@gmail.com
Classifier: Development Status :: 4 - Beta
Classifier: Intended Audience :: End Users/Desktop
Classifier: License :: OSI Approved :: MIT License
Classifier: Programming Language :: Python :: 3
Classifier: Topic :: Games/Entertainment
License-File: LICENSE
Requires-Dist: typer
Requires-Dist: toml
Requires-Dist: pyfiglet
Requires-Dist: asciichartpy
Requires-Dist: asciimatics
Requires-Dist: windows-curses ; platform_system == "Windows"
